{"openapi":"3.0.0","paths":{"/api/v1":{"get":{"operationId":"AppController_getHome","parameters":[],"responses":{"200":{"description":""}},"tags":["App"]}},"/api/v1/files/{filename}":{"get":{"operationId":"AppController_streamFile","parameters":[{"name":"filename","required":true,"in":"path","schema":{"type":"string"}}],"responses":{"200":{"description":""}},"tags":["App"]}},"/api/v1/auth/register":{"post":{"operationId":"AuthController_register","parameters":[],"requestBody":{"required":true,"content":{"application/json":{"schema":{"$ref":"#/components/schemas/RegisterUserDto"}}}},"responses":{"201":{"description":""}},"summary":"Register new User account","tags":["Auth"]}},"/api/v1/auth/login":{"post":{"operationId":"AuthController_signIn","parameters":[],"requestBody":{"required":true,"content":{"application/json":{"schema":{"$ref":"#/components/schemas/LoginUserDto"}}}},"responses":{"200":{"description":""}},"summary":"Login User","tags":["Auth"]}},"/api/v1/auth/change-password":{"post":{"operationId":"AuthController_changePassword","parameters":[],"requestBody":{"required":true,"content":{"application/json":{"schema":{"$ref":"#/components/schemas/ChangePasswordDto"}}}},"responses":{"201":{"description":""}},"tags":["Auth"]}},"/api/v1/auth/forgot-password":{"post":{"operationId":"AuthController_forgotPassword","parameters":[],"responses":{"201":{"description":""}},"tags":["Auth"]}},"/api/v1/auth/reset-password":{"post":{"operationId":"AuthController_resetPassword","parameters":[],"requestBody":{"required":true,"content":{"application/json":{"schema":{"$ref":"#/components/schemas/ResetPasswordDto"}}}},"responses":{"201":{"description":""}},"tags":["Auth"]}}},"info":{"title":"backend_starter_pack","description":"The API Description for Backend Starter Pack","version":"1.0","contact":{}},"tags":[],"servers":[],"components":{"schemas":{"RegisterUserDto":{"type":"object","properties":{}},"LoginUserDto":{"type":"object","properties":{}},"ChangePasswordDto":{"type":"object","properties":{}},"ResetPasswordDto":{"type":"object","properties":{}}}}}